[{"apikey": "eyJrIjoiaWoxY0drNXc4MjBzYXVXWVNSNURISGZjemVEQ0NCOTYiLCJuIjoiZ3JhZmFuYV9hcGlrZXkiLCJpZCI6MX0=", "name": "Samsung-Poc", "url": "http://172.16.30.40:50054/", "report_url": "http://172.16.30.40:50055/", "titles": {"node": "Samsung-Poc-Node_exporter", "binlog": "Samsung-Poc-Binlog", "overview": "Samsung-Poc-Overview", "disk_performance": "Samsung-Poc-Disk-Performance", "tikv": "Samsung-Poc-TiKV", "blackbox_exporter": "Samsung-Poc-Blackbox_exporter", "pd": "Samsung-Poc-PD", "tidb": "Samsung-Poc-TiDB", "kafka_overview": "Samsung-Poc-Kafka-Overview"}, "user": "admin", "password": "admin", "datasource": "samsung-poc"}]
